{
	"configurations" : 
	[
		{
			"directories" : 
			[
				{
					"build" : ".",
					"childIndexes" : 
					[
						1
					],
					"hasInstallRule" : true,
					"jsonFile" : "directory-.-Debug-f5ebdc15457944623624.json",
					"minimumCMakeVersion" : 
					{
						"string" : "3.10"
					},
					"projectIndex" : 0,
					"source" : ".",
					"targetIndexes" : 
					[
						4,
						5,
						6
					]
				},
				{
					"build" : "googletest",
					"childIndexes" : 
					[
						2
					],
					"hasInstallRule" : true,
					"jsonFile" : "directory-googletest-Debug-5680492ebebea2dba35e.json",
					"minimumCMakeVersion" : 
					{
						"string" : "3.16"
					},
					"parentIndex" : 0,
					"projectIndex" : 1,
					"source" : "googletest"
				},
				{
					"build" : "googletest/googlemock",
					"childIndexes" : 
					[
						3
					],
					"hasInstallRule" : true,
					"jsonFile" : "directory-googletest.googlemock-Debug-4581a84ec282a95e7fdf.json",
					"minimumCMakeVersion" : 
					{
						"string" : "3.13"
					},
					"parentIndex" : 1,
					"projectIndex" : 2,
					"source" : "googletest/googlemock",
					"targetIndexes" : 
					[
						0,
						1
					]
				},
				{
					"build" : "googletest/googletest",
					"hasInstallRule" : true,
					"jsonFile" : "directory-googletest.googletest-Debug-7e29ebe4c3c8858c65c4.json",
					"minimumCMakeVersion" : 
					{
						"string" : "3.13"
					},
					"parentIndex" : 2,
					"projectIndex" : 3,
					"source" : "googletest/googletest",
					"targetIndexes" : 
					[
						2,
						3
					]
				}
			],
			"name" : "Debug",
			"projects" : 
			[
				{
					"childIndexes" : 
					[
						1
					],
					"directoryIndexes" : 
					[
						0
					],
					"name" : "gtest",
					"targetIndexes" : 
					[
						4,
						5,
						6
					]
				},
				{
					"childIndexes" : 
					[
						2
					],
					"directoryIndexes" : 
					[
						1
					],
					"name" : "googletest-distribution",
					"parentIndex" : 0
				},
				{
					"childIndexes" : 
					[
						3
					],
					"directoryIndexes" : 
					[
						2
					],
					"name" : "gmock",
					"parentIndex" : 1,
					"targetIndexes" : 
					[
						0,
						1
					]
				},
				{
					"directoryIndexes" : 
					[
						3
					],
					"name" : "gtest",
					"parentIndex" : 2,
					"targetIndexes" : 
					[
						2,
						3
					]
				}
			],
			"targets" : 
			[
				{
					"directoryIndex" : 2,
					"id" : "gmock::@d68da25237a7ca2351af",
					"jsonFile" : "target-gmock-Debug-76f7729ee9ea59126362.json",
					"name" : "gmock",
					"projectIndex" : 2
				},
				{
					"directoryIndex" : 2,
					"id" : "gmock_main::@d68da25237a7ca2351af",
					"jsonFile" : "target-gmock_main-Debug-a7c0c2c6ed73bbe40a53.json",
					"name" : "gmock_main",
					"projectIndex" : 2
				},
				{
					"directoryIndex" : 3,
					"id" : "gtest::@f95b5c00bd49b3b4698d",
					"jsonFile" : "target-gtest-Debug-0ed03dd323fb5e96b2e7.json",
					"name" : "gtest",
					"projectIndex" : 3
				},
				{
					"directoryIndex" : 3,
					"id" : "gtest_main::@f95b5c00bd49b3b4698d",
					"jsonFile" : "target-gtest_main-Debug-1c7f702186a7bbe01b7a.json",
					"name" : "gtest_main",
					"projectIndex" : 3
				},
				{
					"directoryIndex" : 0,
					"id" : "main_app::@6890427a1f51a3e7e1df",
					"jsonFile" : "target-main_app-Debug-848701c5ff9a69c22827.json",
					"name" : "main_app",
					"projectIndex" : 0
				},
				{
					"directoryIndex" : 0,
					"id" : "test_app::@6890427a1f51a3e7e1df",
					"jsonFile" : "target-test_app-Debug-6bf846988c7b5bbc7d34.json",
					"name" : "test_app",
					"projectIndex" : 0
				},
				{
					"directoryIndex" : 0,
					"id" : "vowel_lib::@6890427a1f51a3e7e1df",
					"jsonFile" : "target-vowel_lib-Debug-a3e41d165bdf713fac39.json",
					"name" : "vowel_lib",
					"projectIndex" : 0
				}
			]
		}
	],
	"kind" : "codemodel",
	"paths" : 
	{
		"build" : "/Users/matveyd/CLionProjects/OOP/Lab1/cmake-build-debug",
		"source" : "/Users/matveyd/CLionProjects/OOP/Lab1"
	},
	"version" : 
	{
		"major" : 2,
		"minor" : 6
	}
}
